<?xml version="1.0"?>
<LoadedArticle xmlns:xsi="http://www.w3.org/2001/XMLSchema-instance" xmlns:xsd="http://www.w3.org/2001/XMLSchema">
  <Id>0</Id>
  <Url>http://www.finam.ru/analysis/marketnews/na-sleduyusheiy-nedele-umerenno-negativnaya-dinamika-na-rossiiyskom-rynke-akciiy-budet-soxranyatsya-20140919-1820/</Url>
  <Title>На следующей неделе умеренно негативная динамика на российском рынке акций будет сохраняться</Title>
  <Content>&lt;p&gt;Объявление предварительных итогов референдума о независимости Шотландии привело к снижению котировок российских акций. Участники финансовых рынков надеялись, что в случае поддержки в Шотландии идеи отделения от Великобритании снизится напряженность на востоке Украины. Мы склоняемся к тому, что результаты голосования не будут оказывать влияния в дальнейшем на торги, и основным фактором станут ожидания связанные с зарубежными санкциями, такие как перспективы сохранения подключения российских банков к SWIFT. В целом мы ожидаем, что на следующей неделе сохранится умеренно негативная динамика на российском рынке акций.&lt;/p&gt;&lt;p&gt;На московской бирже рост котировок отмечается в бумагах производителей удобрений. В лидерах бумаги Уралкалия после появления новостей об освобождения Владислава Баумгертнера, бывшего президента компании. Фосагро подорожал после утверждения промежуточных дивидендов. В данном случае можно утверждать, что рост интереса к данным акциям не связан с конъюнктурой и операционной деятельностью на рынке удобрений.&lt;/p&gt;</Content>
  <Author>Халиков Айрат</Author>
  <Company> ИК Велес Капитал</Company>
  <PublishDate>2014-09-19T18:20:00</PublishDate>
</LoadedArticle>