<?xml version="1.0"?>
<LoadedArticle xmlns:xsi="http://www.w3.org/2001/XMLSchema-instance" xmlns:xsd="http://www.w3.org/2001/XMLSchema">
  <Id>0</Id>
  <Url>http://www.finam.ru/analysis/marketnews/v-techenie-dnya-kotirovki-pary-usd-rub-mogut-dostignut-urovnya-47-47-2-20141111-1330/</Url>
  <Title>В течение дня котировки пары USD/RUB могут достигнуть уровня 47-47,2</Title>
  <Content>&lt;p&gt;Вторник небогат на статистику. Япония предоставит данные по банковскому кредитованию и сальдо текущего счета. Великобритания опубликует данные по розничной торговле от BRC. Австралия опубликует индекс цен на жилье за третий квартал. США предоставит данные по индексу розничных продаж Redbook.&lt;/p&gt;&lt;p&gt;Валютная пара EUR/USD в случае продолжении падения, вероятно, может отправиться тестировать уровень поддержки в области 1.2350 и закрепиться ниже. &lt;/p&gt;&lt;p&gt;Что касается российского рубля, то ситуация следующая: вчера В. В. Путин сделал ряд заявлений, на фоне которых рубль резко укрепился. Однако во вторник, по нашему мнению, котировки по парам USD/RUB и EUR/RUB начнут двигаться вверх, и укрепление рубля было краткосрочной реакцией рынка на заявление президента РФ. К тому же цены на нефть вернулись в район 82$ за баррель. Предполагаем, что в течение дня котировки достигнут уровня 47.00-47.20 по паре USD/RUB. и 58.00-58.30 по паре EUR/RUB.&lt;/p&gt;</Content>
  <Author>Гитес Артем</Author>
  <Company> Банк ГЛОБЭКС</Company>
  <PublishDate>2014-11-11T13:30:00</PublishDate>
</LoadedArticle>