<?xml version="1.0"?>
<LoadedArticle xmlns:xsi="http://www.w3.org/2001/XMLSchema-instance" xmlns:xsd="http://www.w3.org/2001/XMLSchema">
  <Id>0</Id>
  <Url>http://www.finam.ru/analysis/marketnews/u-pokupateleiy-poyavilsya-shans-podnyat-indeks-mmvb-v-raiyon-otmetok-1440-1450-punktov-20140923-1910/</Url>
  <Title>У покупателей появился шанс поднять индекс ММВБ в район отметок 1440-1450 пунктов</Title>
  <Content>&lt;p&gt;Торги во вторник на российском фондовом рынке завершились на позитивной волне. Индекс ММВБ не дошел до минимумов предыдущего снижения, расположенных у отметки 1390 пунктов, а нашел поддержку у отметки 1413 пунктов и начал от нее расти. При этом под закрытие торговой сессии котировки преодолели уровни 1420-1425 пунктов, которые сдерживали движение цен наверх в течение дня. Таким образом, у покупателей появился шанс развить свой успех и поднять индекс в район отметок 1440-1450 пунктов, где располагаются значимые уровни сопротивления.&lt;/p&gt;</Content>
  <Author>Маликов Алексей</Author>
  <Company> ИК ТРЕЙД-ПОРТАЛ</Company>
  <PublishDate>2014-09-23T19:10:00</PublishDate>
</LoadedArticle>