<?xml version="1.0"?>
<LoadedArticle xmlns:xsi="http://www.w3.org/2001/XMLSchema-instance" xmlns:xsd="http://www.w3.org/2001/XMLSchema">
  <Id>0</Id>
  <Url>http://www.finam.ru/analysis/marketnews/pokupateli-otstoyali-podderzhku-po-indeksu-mmvb-na-urovnyax-1400-1380-punktov-i-pereshli-v-kontrnastuplenie-20140903-1901/</Url>
  <Title>Покупатели отстояли поддержку по индексу ММВБ на уровнях 1400-1380 пунктов и перешли в контрнаступление</Title>
  <Content>&lt;p&gt;Российский рынок акций на торгах в среду демонстрирует существенный рост. Покупатели отстояли поддержку по индексу ММВБ на уровнях 1400-1380 пунктов и перешли в контрнаступление. Надо сказать, оно им удалось. Практически за одну торговую сессию индекс вернулся к уровням, близким к максимумам предыдущей волны роста. Здесь в районе отметок 1450 -1460 пунктов покупатели вновь столкнутся с возрастающим предложением. Тем более что спровоцировавшая массовое закрытие коротких позиций, приведшая к столь стремительному росту цен новость, не совсем корректная и уже отыграна рынком с инерцией.&lt;/p&gt;</Content>
  <Author>Маликов Алексей</Author>
  <Company> ИК ТРЕЙД-ПОРТАЛ</Company>
  <PublishDate>2014-09-03T19:01:00</PublishDate>
</LoadedArticle>