<?xml version="1.0"?>
<LoadedArticle xmlns:xsi="http://www.w3.org/2001/XMLSchema-instance" xmlns:xsd="http://www.w3.org/2001/XMLSchema">
  <Id>0</Id>
  <Url>http://www.finam.ru/analysis/marketnews/prodolzhenie-oslableniya-nacionalnoiy-valyuty-vpolne-veroyatno-v-svete-novoiy-volny-snizheniya-nefti-20141105-1440/</Url>
  <Title>Продолжение ослабления национальной валюты вполне вероятно в свете новой волны снижения нефти</Title>
  <Content>&lt;p&gt;В ходе сегодняшних валютных торгов на Московской бирже курсы доллара США (44.4805 рубль/доллар; +87.25 коп.) и единой европейской валюты (55.5280 рубль/евро; +103.25 коп.) заметно растут. В результате такой динамики стоимость бивалютной корзины формируется на уровне 49.4366 рубля (+92.92 коп.). Разочарование и уныние - никак иначе текущую динамику не назовешь. Кому-кому, а Банку России в этой ситуации не позавидуешь, так как он, по сути, выступил провокатором. Все увидели, что даже такое резкое поднятие ключевой ставки ситуацию выправить не может. В целом, продолжение ослабления национальной валюты вполне вероятно, особенно, в свете новой волны ослабления нефти. Баррель Brent опускался сегодня ниже отметки $82. А меж тем интервенции продолжаются (валюты продают на 100 с лишним млрд рублей в день), рубль же продолжает стоять у разбитого корыта.&lt;/p&gt;</Content>
  <Author>Алин Сергей</Author>
  <Company> ИГ Норд-Капитал</Company>
  <PublishDate>2014-11-05T14:40:00</PublishDate>
</LoadedArticle>